ChemicalFormulaParser/__init__.py
ChemicalFormulaParser/atom.py
ChemicalFormulaParser/molecule.py
ChemicalFormulaParser/molecule_parser.py
tests/__init__.py
tests/test_atom.py
tests/test_molecule.py
tests/test_molecule_parser.py
molecule_parser-0.0.1.dist-info/METADATA
molecule_parser-0.0.1.dist-info/WHEEL
molecule_parser-0.0.1.dist-info/top_level.txt
molecule_parser-0.0.1.dist-info/RECORD
