Metadata-Version: 2.1
Name: molecule-parser
Version: 0.0.1
Summary: A package to parse chemical formulas
Home-page: https://github.com/SebastienEveno/molecule-parser
Author: Sebastien Eveno
Author-email: sebastien.louis.eveno@gmail.com
License: UNKNOWN
Keywords: python,chemical formula parser package
Platform: UNKNOWN
Classifier: Programming Language :: Python :: 2
Classifier: Programming Language :: Python :: 3
Classifier: License :: OSI Approved :: MIT License
Classifier: Operating System :: OS Independent
Requires-Python: >=3.6
